shopyo_i18n/__init__.py
shopyo_i18n/forms.py
shopyo_i18n/helpers.py
shopyo_i18n/info.json
shopyo_i18n/models.py
shopyo_i18n/view.py
shopyo_i18n/templates/shopyo_i18n/dashboard.html
shopyo_i18n/templates/shopyo_i18n/blocks/sidebar.html
shopyo_i18n/tests/test_i18n_functional.py
shopyo_i18n/tests/test_i18n_models.py
shopyo_i18n-1.2.0.dist-info/METADATA
shopyo_i18n-1.2.0.dist-info/WHEEL
shopyo_i18n-1.2.0.dist-info/top_level.txt
shopyo_i18n-1.2.0.dist-info/RECORD
